exifool/__init__.py
exifool/cli.py
exifool/errors.py
exifool/extractor.py
exifool/pdf.py
exifool/utility.py
exifool-0.1.8.dist-info/METADATA
exifool-0.1.8.dist-info/WHEEL
exifool-0.1.8.dist-info/entry_points.txt
exifool-0.1.8.dist-info/top_level.txt
exifool-0.1.8.dist-info/RECORD
