Metadata-Version: 2.2
Name: exifool
Version: 0.1.8
Summary: Metadata retrieval tool
Requires-Python: >=3.13
Requires-Dist: click>=8.1.8
Requires-Dist: pypdf>=5.2.0
Requires-Dist: rich>=13.9.4
